rendergfm/__init__.py
rendergfm/__main__.py
RenderGFM-1.0.1.dist-info/LICENSE.txt
RenderGFM-1.0.1.dist-info/METADATA
RenderGFM-1.0.1.dist-info/WHEEL
RenderGFM-1.0.1.dist-info/entry_points.txt
RenderGFM-1.0.1.dist-info/top_level.txt
RenderGFM-1.0.1.dist-info/RECORD
