Metadata-Version: 2.1
Name: RenderGFM
Version: 1.0.1
Summary: Command-line tool to render Markdown to HTML using the GitHub API
Home-page: https://brettcsmith.org/RenderGFM
Author: Brett Smith
Author-email: brettcsmith@brettcsmith.org
License: Apache License 2.0
Project-URL: Documentation, https://brettcsmith.org/RenderGFM
Project-URL: Source, https://brettcsmith.org/RenderGFM
Platform: UNKNOWN
Classifier: Development Status :: 5 - Production/Stable
Classifier: Environment :: Console
Classifier: Intended Audience :: End Users/Desktop
Classifier: Operating System :: OS Independent
Classifier: Programming Language :: Python :: 3
Classifier: Programming Language :: Python :: 3.7
Classifier: Programming Language :: Python :: 3.8
Classifier: Programming Language :: Python :: 3.9
Classifier: Topic :: Text Processing :: Markup :: HTML
Classifier: Topic :: Text Processing :: Markup :: Markdown
Classifier: Typing :: Typed
Requires-Python: >=3.7
License-File: LICENSE.txt
Requires-Dist: requests (>=2.20)
